{
  "products": [
    {
      "name": "블루필 3종(사운드팝/넥쿨러/제트 파우치팬)",
      "brandName": "블루필",
      "productName": "파우치팬/넥쿨러/스피커",
      "campaignType": "공동구매",
      "category": "육아·키즈",
      "usp": "① 미니 제트 파우치팬\n✔️ 76g 초경량 / 20,000RPM 제트 모터\n✔️ 전용 파우치+키링 기본 구성\n→ 휴대용겸 가방키링으로 달기 너무 좋아요\n(공구링크) https://buly.kr/C0BcesR\n\n② 아이스 넥쿨러\n✔️ 얼음물 10분이면 준비 완료\n✔️ 최대 2.5시간 지속 / 누적 120만 개 판매\n→ 여름 출근·운동·등하원 콘텐츠에 적합\n(공구링크) https://buly.kr/74YPC3V\n\n③ 사운드팝 3in1 스피커\n✔️ 스피커 + 그립홀더 + 거치대\n✔️ 91g 초경량 / 5W 출력 / 최대 16시간 사용\n→ 영상·음악 콘텐츠에 활용도 높은 아이템\n(공구링크) https://buly.kr/2qaDeSl",
      "offerMessage": "올 여름 필수품 공구핫템💗 블루필 파우치팬/넥쿨러/스피커\n\n안녕하세요~ \n여름 시즌 3가지 보여드리고 싶어서 연락드려요 !\n실용성, 편리함, 디자인까지 모두 공구핫템이에요😊\n\n① 미니 제트 파우치팬\n✔️ 76g 초경량 / 20,000RPM 제트 모터\n✔️ 전용 파우치 + 키링 기본 구성\n(공구링크) https://buly.kr/C0BcesR\n\n② 아이스 넥쿨러\n✔️ 얼음물 10분이면 준비 완료\n✔️ 최대 2.5시간 지속 / 누적 120만 개 판매\n(공구링크) https://buly.kr/74YPC3V\n\n③ 사운드팝 3in1 스피커\n✔️ 스피커+그립홀더+거치대\n✔️ 91g 초경량 / 최대 16시간 사용\n(공구링크) https://buly.kr/2qaDeSl\n\n제품 1~2개만 선택 진행도 가능하고, 여름 시즌 묶음으로 기획해도 좋아 보여 제안드립니다.\n궁금하신 제품은 제안서 보내드릴게요 ! \n\n혹시 관심 있으시면 편하게 연락주세요 🙏",
      "photos": [
        "c:/proj/test/assets/1775096550219_jaboia.png"
      ]
    }
  ]
}